{
  "0hmxbot": {
    "reviewsReceived": 0,
    "rejectionsReceived": 0,
    "approvalsReceived": 0,
    "staffReviewedPrs": 0,
    "staffRejectionsReceived": 0,
    "staffApprovalsReceived": 0,
    "staffReviewedPrLinks": [],
    "approvalsGiven": 0,
    "rejectionsGiven": 0,
    "prsOpened": 3,
    "prsMerged": 0,
    "issuesCreated": 0,
    "bountiedIssuesCount": 0,
    "bountiedIssuesTotal": 0,
    "distinctPrsReviewedNonCodeOwner": 0,
    "discussionComments": 0,
    "discussionNormalComments": 0,
    "discussionGreatInformativeComments": 0,
    "discussionIncredibleComments": 0,
    "score": 0,
    "stars": ""
  },
  "Abse2001": {
    "reviewsReceived": 1,
    "rejectionsReceived": 0,
    "approvalsReceived": 1,
    "staffReviewedPrs": 1,
    "staffRejectionsReceived": 0,
    "staffApprovalsReceived": 1,
    "staffReviewedPrLinks": [
      {
        "number": 71,
        "url": "https://github.com/tscircuit/circuit-json-to-step/pull/71",
        "title": "Add STEP styling pipeline with face-level color support and optimized style reuse",
        "staffApprovals": 1,
        "staffRejections": 0
      }
    ],
    "approvalsGiven": 0,
    "rejectionsGiven": 0,
    "prsOpened": 3,
    "prsMerged": 1,
    "issuesCreated": 0,
    "bountiedIssuesCount": 0,
    "bountiedIssuesTotal": 0,
    "distinctPrsReviewedNonCodeOwner": 0,
    "discussionComments": 0,
    "discussionNormalComments": 0,
    "discussionGreatInformativeComments": 0,
    "discussionIncredibleComments": 0,
    "reposOwned": [
      {
        "repo": "tscircuit/pcb-viewer",
        "paths": [
          "*"
        ]
      }
    ],
    "score": 4,
    "stars": "⭐",
    "major": 1,
    "minor": 0,
    "tiny": 0
  },
  "AnasSarkiz": {
    "reviewsReceived": 1,
    "rejectionsReceived": 0,
    "approvalsReceived": 1,
    "staffReviewedPrs": 0,
    "staffRejectionsReceived": 0,
    "staffApprovalsReceived": 0,
    "staffReviewedPrLinks": [],
    "approvalsGiven": 0,
    "rejectionsGiven": 0,
    "prsOpened": 7,
    "prsMerged": 5,
    "issuesCreated": 0,
    "bountiedIssuesCount": 0,
    "bountiedIssuesTotal": 0,
    "distinctPrsReviewedNonCodeOwner": 0,
    "discussionComments": 0,
    "discussionNormalComments": 0,
    "discussionGreatInformativeComments": 0,
    "discussionIncredibleComments": 0,
    "score": 5.5,
    "stars": "⭐",
    "major": 0,
    "minor": 1,
    "tiny": 4
  },
  "Emanuelgm1998": {
    "reviewsReceived": 0,
    "rejectionsReceived": 0,
    "approvalsReceived": 0,
    "staffReviewedPrs": 0,
    "staffRejectionsReceived": 0,
    "staffApprovalsReceived": 0,
    "staffReviewedPrLinks": [],
    "approvalsGiven": 0,
    "rejectionsGiven": 0,
    "prsOpened": 1,
    "prsMerged": 0,
    "issuesCreated": 0,
    "bountiedIssuesCount": 0,
    "bountiedIssuesTotal": 0,
    "distinctPrsReviewedNonCodeOwner": 0,
    "discussionComments": 0,
    "discussionNormalComments": 0,
    "discussionGreatInformativeComments": 0,
    "discussionIncredibleComments": 0,
    "score": 0,
    "stars": ""
  },
  "MustafaMulla29": {
    "reviewsReceived": 14,
    "rejectionsReceived": 2,
    "approvalsReceived": 7,
    "staffReviewedPrs": 3,
    "staffRejectionsReceived": 2,
    "staffApprovalsReceived": 3,
    "staffReviewedPrLinks": [
      {
        "number": 591,
        "url": "https://github.com/tscircuit/footprinter/pull/591",
        "title": "Update remaining courtyard geometry and add parity tests",
        "staffApprovals": 1,
        "staffRejections": 2
      },
      {
        "number": 585,
        "url": "https://github.com/tscircuit/footprinter/pull/585",
        "title": "Use generic body-based courtyard for SON parity",
        "staffApprovals": 1,
        "staffRejections": 0
      },
      {
        "number": 588,
        "url": "https://github.com/tscircuit/footprinter/pull/588",
        "title": "feat(vssop): switch to generic body-based courtyard",
        "staffApprovals": 1,
        "staffRejections": 0
      }
    ],
    "approvalsGiven": 0,
    "rejectionsGiven": 0,
    "prsOpened": 9,
    "prsMerged": 7,
    "issuesCreated": 0,
    "bountiedIssuesCount": 0,
    "bountiedIssuesTotal": 0,
    "distinctPrsReviewedNonCodeOwner": 0,
    "discussionComments": 0,
    "discussionNormalComments": 0,
    "discussionGreatInformativeComments": 0,
    "discussionIncredibleComments": 0,
    "score": 11,
    "stars": "⭐⭐",
    "major": 1,
    "minor": 1,
    "tiny": 5
  },
  "ShiboSoftwareDev": {
    "reviewsReceived": 0,
    "rejectionsReceived": 0,
    "approvalsReceived": 0,
    "staffReviewedPrs": 0,
    "staffRejectionsReceived": 0,
    "staffApprovalsReceived": 0,
    "staffReviewedPrLinks": [],
    "approvalsGiven": 1,
    "rejectionsGiven": 0,
    "prsOpened": 0,
    "prsMerged": 0,
    "issuesCreated": 0,
    "bountiedIssuesCount": 0,
    "bountiedIssuesTotal": 0,
    "distinctPrsReviewedNonCodeOwner": 1,
    "distinctPrsReviewedAsCodeOwner": 0,
    "score": 0,
    "stars": ""
  },
  "mitchellecm7": {
    "reviewsReceived": 0,
    "rejectionsReceived": 0,
    "approvalsReceived": 0,
    "staffReviewedPrs": 0,
    "staffRejectionsReceived": 0,
    "staffApprovalsReceived": 0,
    "staffReviewedPrLinks": [],
    "approvalsGiven": 0,
    "rejectionsGiven": 0,
    "prsOpened": 2,
    "prsMerged": 0,
    "issuesCreated": 0,
    "bountiedIssuesCount": 0,
    "bountiedIssuesTotal": 0,
    "distinctPrsReviewedNonCodeOwner": 0,
    "discussionComments": 0,
    "discussionNormalComments": 0,
    "discussionGreatInformativeComments": 0,
    "discussionIncredibleComments": 0,
    "score": 0,
    "stars": ""
  },
  "mohan-bee": {
    "reviewsReceived": 3,
    "rejectionsReceived": 1,
    "approvalsReceived": 1,
    "staffReviewedPrs": 2,
    "staffRejectionsReceived": 1,
    "staffApprovalsReceived": 1,
    "staffReviewedPrLinks": [
      {
        "number": 374,
        "url": "https://github.com/tscircuit/easyeda-converter/pull/374",
        "title": "Preserve {NAME}  placeholder in generated silkscreen text",
        "staffApprovals": 1,
        "staffRejections": 0
      },
      {
        "number": 26,
        "url": "https://github.com/tscircuit/circuit-json-to-tscircuit/pull/26",
        "title": "Fix source‑subcircuit imports by preserving connectivity and props",
        "staffApprovals": 0,
        "staffRejections": 1
      }
    ],
    "approvalsGiven": 0,
    "rejectionsGiven": 0,
    "prsOpened": 2,
    "prsMerged": 1,
    "issuesCreated": 0,
    "bountiedIssuesCount": 0,
    "bountiedIssuesTotal": 0,
    "distinctPrsReviewedNonCodeOwner": 0,
    "discussionComments": 0,
    "discussionNormalComments": 0,
    "discussionGreatInformativeComments": 0,
    "discussionIncredibleComments": 0,
    "score": 4,
    "stars": "⭐",
    "major": 1,
    "minor": 0,
    "tiny": 0
  },
  "seveibar": {
    "reviewsReceived": 2,
    "rejectionsReceived": 0,
    "approvalsReceived": 0,
    "staffReviewedPrs": 0,
    "staffRejectionsReceived": 0,
    "staffApprovalsReceived": 0,
    "staffReviewedPrLinks": [],
    "approvalsGiven": 9,
    "rejectionsGiven": 3,
    "prsOpened": 16,
    "prsMerged": 8,
    "issuesCreated": 0,
    "bountiedIssuesCount": 0,
    "bountiedIssuesTotal": 0,
    "distinctPrsReviewedNonCodeOwner": 1,
    "discussionComments": 0,
    "discussionNormalComments": 0,
    "discussionGreatInformativeComments": 0,
    "discussionIncredibleComments": 0,
    "distinctPrsReviewedAsCodeOwner": 6,
    "score": 20,
    "stars": "⭐⭐",
    "major": 3,
    "minor": 2,
    "tiny": 3
  },
  "techmannih2": {
    "reviewsReceived": 0,
    "rejectionsReceived": 0,
    "approvalsReceived": 0,
    "staffReviewedPrs": 0,
    "staffRejectionsReceived": 0,
    "staffApprovalsReceived": 0,
    "staffReviewedPrLinks": [],
    "approvalsGiven": 0,
    "rejectionsGiven": 0,
    "prsOpened": 2,
    "prsMerged": 0,
    "issuesCreated": 0,
    "bountiedIssuesCount": 0,
    "bountiedIssuesTotal": 0,
    "distinctPrsReviewedNonCodeOwner": 0,
    "distinctPrsReviewedAsCodeOwner": 0,
    "score": 0,
    "stars": ""
  },
  "tscircuitbot": {
    "reviewsReceived": 0,
    "rejectionsReceived": 0,
    "approvalsReceived": 0,
    "staffReviewedPrs": 0,
    "staffRejectionsReceived": 0,
    "staffApprovalsReceived": 0,
    "staffReviewedPrLinks": [],
    "approvalsGiven": 0,
    "rejectionsGiven": 0,
    "prsOpened": 7,
    "prsMerged": 7,
    "issuesCreated": 0,
    "bountiedIssuesCount": 0,
    "bountiedIssuesTotal": 0,
    "distinctPrsReviewedNonCodeOwner": 0,
    "discussionComments": 0,
    "discussionNormalComments": 0,
    "discussionGreatInformativeComments": 0,
    "discussionIncredibleComments": 0,
    "score": 7,
    "stars": "⭐",
    "major": 0,
    "minor": 0,
    "tiny": 7
  }
}